mb_cli/__init__.py
mb_cli/cli/__init__.py
mb_cli/cli/api.py
mb_cli/cli/ex.py
mb_cli/cli/validation.py
mb_cli/main.py
mb_cli/settings.py
mb_cli-2.0.0.dist-info/LICENSE
mb_cli-2.0.0.dist-info/METADATA
mb_cli-2.0.0.dist-info/WHEEL
mb_cli-2.0.0.dist-info/entry_points.txt
mb_cli-2.0.0.dist-info/RECORD
