Metadata-Version: 2.1
Name: mb-cli
Version: 2.0.0
Summary: Majestic Bank CLI application
Home-page: https://notmtth.xyz
License: GPL-3
Keywords: majesticbank,cryptocurrency,monero,cli
Author: NotMtth
Author-email: notmtth@xmpp.is
Requires-Python: >=3.9,<4.0
Classifier: License :: Other/Proprietary License
Classifier: Programming Language :: Python :: 3
Classifier: Programming Language :: Python :: 3.9
Classifier: Programming Language :: Python :: 3.10
Classifier: Programming Language :: Python :: 3.11
Requires-Dist: httpx (>=0.24.0,<0.25.0)
Requires-Dist: inquirerpy (>=0.3.4,<0.4.0)
Requires-Dist: qrcode (>=7.4.2,<8.0.0)
Requires-Dist: rich (>=13.3.5,<14.0.0)
Requires-Dist: socksio (>=1.0.0,<2.0.0)
Requires-Dist: typer (>=0.9.0,<0.10.0)
Project-URL: Repository, https://codeberg.org/NotMtth/mb-cli
